hippomaps/__init__.py
hippomaps/build_mpc.py
hippomaps/config.py
hippomaps/fetcher.py
hippomaps/moran.py
hippomaps/plotting.py
hippomaps/stats.py
hippomaps/utils.py
hippomaps/resources/.DS_Store
hippomaps/resources/2Dcontextualize/initialHippoMaps.npz
hippomaps/resources/canonical_surfs/canonical_surfs.m
hippomaps/resources/canonical_surfs/tpl-avg_space-canonical_den-0p5mm_label-dentate_midthickness.surf.gii
hippomaps/resources/canonical_surfs/tpl-avg_space-canonical_den-0p5mm_label-dentate_surfarea.shape.gii
hippomaps/resources/canonical_surfs/tpl-avg_space-canonical_den-0p5mm_label-hipp_midthickness.surf.gii
hippomaps/resources/canonical_surfs/tpl-avg_space-canonical_den-0p5mm_label-hipp_surfarea.shape.gii
hippomaps/resources/canonical_surfs/tpl-avg_space-canonical_den-1mm_label-dentate_midthickness.surf.gii
hippomaps/resources/canonical_surfs/tpl-avg_space-canonical_den-1mm_label-dentate_surfarea.shape.gii
hippomaps/resources/canonical_surfs/tpl-avg_space-canonical_den-1mm_label-hipp_midthickness.surf.gii
hippomaps/resources/canonical_surfs/tpl-avg_space-canonical_den-1mm_label-hipp_surfarea.shape.gii
hippomaps/resources/canonical_surfs/tpl-avg_space-canonical_den-2mm_label-dentate_midthickness.surf.gii
hippomaps/resources/canonical_surfs/tpl-avg_space-canonical_den-2mm_label-dentate_surfarea.shape.gii
hippomaps/resources/canonical_surfs/tpl-avg_space-canonical_den-2mm_label-hipp_midthickness.surf.gii
hippomaps/resources/canonical_surfs/tpl-avg_space-canonical_den-2mm_label-hipp_surfarea.shape.gii
hippomaps/resources/canonical_surfs/tpl-avg_space-canonical_den-unfoldiso_label-dentate_midthickness.surf.gii
hippomaps/resources/canonical_surfs/tpl-avg_space-canonical_den-unfoldiso_label-dentate_surfarea.shape.gii
hippomaps/resources/canonical_surfs/tpl-avg_space-canonical_den-unfoldiso_label-hipp_midthickness.surf.gii
hippomaps/resources/canonical_surfs/tpl-avg_space-canonical_den-unfoldiso_label-hipp_surfarea.shape.gii
HippoMaps-0.1.17.dist-info/LICENSE
HippoMaps-0.1.17.dist-info/METADATA
HippoMaps-0.1.17.dist-info/WHEEL
HippoMaps-0.1.17.dist-info/top_level.txt
HippoMaps-0.1.17.dist-info/RECORD
