Metadata-Version: 2.1
Name: HippoMaps
Version: 0.1.17
Summary: A toolbox for viewing, manipulating, and additional actions on HippUnfold outputs
Home-page: https://github.com/jordandekraker/hippomaps
Author: Jordan DeKraker
Author-email: jordandekraker@gmail.com
License: GPL-3.0 license
Keywords: hippunfold registration
Classifier: Intended Audience :: Science/Research
Classifier: Intended Audience :: Developers
Classifier: Topic :: Software Development :: Build Tools
Classifier: Topic :: Scientific/Engineering
Classifier: Programming Language :: Python :: 3.7
Classifier: Programming Language :: Python :: 3.8
Classifier: Programming Language :: Python :: 3.9
Requires-Python: >=3.7.0
License-File: LICENSE
Requires-Dist: Path >=16.4.0
Requires-Dist: joblib
Requires-Dist: brainspace >=0.1.2
Requires-Dist: nibabel >=3.2.2
Requires-Dist: nilearn >=0.7.0
Requires-Dist: numpy <2.0.0,>=1.23.1
Requires-Dist: pandas >=0.23
Requires-Dist: scipy >=1.3.3
Requires-Dist: matplotlib >=2.0.0
Requires-Dist: pygeodesic >=0.1.8
Requires-Dist: wget >=3.2
Requires-Dist: eigenstrapping >=0.1
Requires-Dist: adjusttext >=1.3.0
Requires-Dist: pathlib
Requires-Dist: parspin
Requires-Dist: tabulate
Requires-Dist: umap-learn >=0.5.5
Provides-Extra: dev
Requires-Dist: gitpython ; extra == 'dev'
Requires-Dist: hcp-utils ; extra == 'dev'
Requires-Dist: mypy ; extra == 'dev'
Requires-Dist: plotly ; extra == 'dev'
Requires-Dist: pytest ; extra == 'dev'
